build_vocabulary/__init__.py
build_vocabulary/file_reader.py
build_vocabulary/main.py
build_vocabulary/.assert/60000.txt
build_vocabulary/.assert/nltk_data/corpora/wordnet.zip
build_vocabulary/.assert/nltk_data/taggers/averaged_perceptron_tagger.zip
build_vocabulary-0.1.9.dist-info/LICENSE
build_vocabulary-0.1.9.dist-info/METADATA
build_vocabulary-0.1.9.dist-info/WHEEL
build_vocabulary-0.1.9.dist-info/entry_points.txt
build_vocabulary-0.1.9.dist-info/top_level.txt
build_vocabulary-0.1.9.dist-info/RECORD
